mdareporter/__init__.py
mdareporter/_version.py
mdareporter/mdareporter.py
mdareporter/.pytest_cache/.gitignore
mdareporter/.pytest_cache/CACHEDIR.TAG
mdareporter/.pytest_cache/README.md
mdareporter/.pytest_cache/v/cache/nodeids
mdareporter/.pytest_cache/v/cache/stepwise
mdareporter/data/README.md
mdareporter/data/__init__.py
mdareporter/data/files.py
mdareporter/data/mda.txt
mdareporter/data/villin.pdb
mdareporter/openmm_mdanalysis_reporter.egg-info/PKG-INFO
mdareporter/openmm_mdanalysis_reporter.egg-info/SOURCES.txt
mdareporter/openmm_mdanalysis_reporter.egg-info/dependency_links.txt
mdareporter/openmm_mdanalysis_reporter.egg-info/requires.txt
mdareporter/openmm_mdanalysis_reporter.egg-info/top_level.txt
mdareporter/tests/__init__.py
mdareporter/tests/conftest.py
mdareporter/tests/test_mdareporter.py
mdareporter/tests/utils.py
mdareporter/tests/.pytest_cache/.gitignore
mdareporter/tests/.pytest_cache/CACHEDIR.TAG
mdareporter/tests/.pytest_cache/README.md
mdareporter/tests/.pytest_cache/v/cache/lastfailed
mdareporter/tests/.pytest_cache/v/cache/nodeids
mdareporter/tests/.pytest_cache/v/cache/stepwise
openmm_mdanalysis_reporter-0.1.dist-info/AUTHORS.md
openmm_mdanalysis_reporter-0.1.dist-info/LICENSE
openmm_mdanalysis_reporter-0.1.dist-info/METADATA
openmm_mdanalysis_reporter-0.1.dist-info/WHEEL
openmm_mdanalysis_reporter-0.1.dist-info/top_level.txt
openmm_mdanalysis_reporter-0.1.dist-info/RECORD
