Metadata-Version: 2.1
Name: openmm-mdanalysis-reporter
Version: 0.1
Summary: MDAnalysis based reporter for OpenMM
Author: Stephen Farr
Author-email: Stephen Farr <stephen.farr@ed.ac.uk>
Maintainer-email: Stephen Farr <stephen.farr@ed.ac.uk>
License: MIT License
Keywords: molecular simulations
Requires-Python: >=3.9
License-File: LICENSE
License-File: AUTHORS.md
Requires-Dist: MDAnalysis (>=2.0.0)
Provides-Extra: doc
Requires-Dist: sphinx ; extra == 'doc'
Requires-Dist: sphinx-rtd-theme ; extra == 'doc'
Provides-Extra: test
Requires-Dist: pytest (>=6.0) ; extra == 'test'
Requires-Dist: pytest-xdist (>=2.5) ; extra == 'test'
Requires-Dist: pytest-cov (>=3.0) ; extra == 'test'
